uv_outdated/__init__.py
uv_outdated/__main__.py
uv_outdated/utils.py
uv_outdated-1.0.4.dist-info/licenses/LICENSE
uv_outdated-1.0.4.dist-info/METADATA
uv_outdated-1.0.4.dist-info/WHEEL
uv_outdated-1.0.4.dist-info/entry_points.txt
uv_outdated-1.0.4.dist-info/top_level.txt
uv_outdated-1.0.4.dist-info/RECORD
