Metadata-Version: 2.4
Name: uv-outdated
Version: 1.0.4
Summary: Show uv outdated packages in a nicer way
Author: Simon Percivall
License-Expression: MIT
Project-URL: Repository, https://github.com/simonpercivall/uv-outdated
Project-URL: Changelog, https://github.com/simonpercivall/uv-outdated/blob/main/CHANGELOG.md
Project-URL: Releases, https://github.com/simonpercivall/uv-outdated/releases
Keywords: requirements,packaging
Requires-Python: >=3.12
License-File: LICENSE
Requires-Dist: packaging>=25.0
Requires-Dist: pydantic>=2.11.7
Requires-Dist: rich>=14.1.0
Requires-Dist: typer>=0.16.0
Dynamic: license-file
